suparunidic/__init__.py
suparunidic/download.py
suparunidic/suparunidic.py
suparunidic/suparmodels/albert-base-japanese-v1/filesize.txt
suparunidic/suparmodels/albert-japanese-v2/filesize.txt
suparunidic/suparmodels/bert-base-ja-cased/filesize.txt
suparunidic/suparmodels/bert-base-japanese-char/filesize.txt
suparunidic/suparmodels/bert-base-japanese-char-extended/filesize.txt
suparunidic/suparmodels/bert-base-japanese-whole-word-masking/filesize.txt
suparunidic/suparmodels/bert-japanese-aozora6m3m-unidic32k-2m/config.json
suparunidic/suparmodels/bert-japanese-aozora6m3m-unidic32k-2m/filesize.txt
suparunidic/suparmodels/bert-japanese-aozora6m3m-unidic32k-2m/tokenizer_config.json
suparunidic/suparmodels/bert-japanese-aozora6m3m-unidic32k-2m/vocab.txt
suparunidic/suparmodels/bert-large-japanese/filesize.txt
suparunidic/suparmodels/bert-large-japanese-char/filesize.txt
suparunidic/suparmodels/bert-large-japanese-char-extended/filesize.txt
suparunidic/suparmodels/bert-small-japanese/filesize.txt
suparunidic/suparmodels/deberta-base-japanese-aozora/filesize.txt
suparunidic/suparmodels/deberta-base-japanese-unidic/filesize.txt
suparunidic/suparmodels/deberta-large-japanese-aozora/filesize.txt
suparunidic/suparmodels/deberta-large-japanese-unidic/filesize.txt
suparunidic/suparmodels/deberta-small-japanese-aozora/filesize.txt
suparunidic/suparmodels/distilbert-base-japanese/filesize.txt
suparunidic/suparmodels/electra-base-japanese-discriminator/filesize.txt
suparunidic/suparmodels/electra-base-japanese-generator/filesize.txt
suparunidic/suparmodels/electra-small-japanese-discriminator/filesize.txt
suparunidic/suparmodels/electra-small-japanese-generator/filesize.txt
suparunidic/suparmodels/japanese-roberta-base/filesize.txt
suparunidic/suparmodels/ku-bert-japanese-large/config.json
suparunidic/suparmodels/ku-bert-japanese-large/filesize.txt
suparunidic/suparmodels/ku-bert-japanese-large/tokenizer_config.json
suparunidic/suparmodels/ku-bert-japanese-large/vocab.txt
suparunidic-1.4.5.dist-info/LICENSE.txt
suparunidic-1.4.5.dist-info/METADATA
suparunidic-1.4.5.dist-info/WHEEL
suparunidic-1.4.5.dist-info/top_level.txt
suparunidic-1.4.5.dist-info/RECORD
