Metadata-Version: 2.1
Name: suparunidic
Version: 1.4.5
Summary: Tokenizer POS-tagger Lemmatizer and Dependency-parser for modern and contemporary Japanese with BERT models
Home-page: https://github.com/KoichiYasuoka/SuPar-UniDic
Author: Koichi Yasuoka
Author-email: yasuoka@kanji.zinbun.kyoto-u.ac.jp
License: MIT
Project-URL: Source, https://github.com/KoichiYasuoka/SuPar-UniDic
Project-URL: Tracker, https://github.com/KoichiYasuoka/SuPar-UniDic/issues
Keywords: NLP Japanese spaCy
Classifier: License :: OSI Approved :: MIT License
Classifier: Programming Language :: Python :: 3
Classifier: Operating System :: OS Independent
Classifier: Topic :: Text Processing :: Linguistic
Classifier: Natural Language :: Japanese
Requires-Python: >=3.7
License-File: LICENSE.txt
Requires-Dist: esupar (>=1.8.7)
Requires-Dist: spacy (>=2.2.2)
Requires-Dist: unidic-lite (>=1.0.8)
Requires-Dist: unidic2ud (>=3.0.6)
